Metadata-Version: 2.4
Name: icet
Version: 3.1
Summary: A Pythonic approach to cluster expansions
Author: The icet developer team
Maintainer: The icet developer team
License: Mozilla Public License Version 2.0
Project-URL: Documentation, https://icet.materialsmodeling.org
Project-URL: Repository, https://gitlab.com/materials-modeling/icet/
Keywords: chemistry,physics,scientific
Classifier: Development Status :: 5 - Production/Stable
Classifier: Operating System :: OS Independent
Classifier: Programming Language :: Python :: 3 :: Only
Classifier: Programming Language :: Python :: 3
Classifier: Programming Language :: Python :: 3.9
Classifier: Programming Language :: Python :: 3.10
Classifier: Programming Language :: Python :: 3.11
Classifier: Programming Language :: Python :: 3.12
Classifier: Intended Audience :: Science/Research
Requires-Python: >=3.9
License-File: LICENSE
Requires-Dist: ase
Requires-Dist: numba>=0.55
Requires-Dist: numpy>=1.18
Requires-Dist: pandas>=0.23
Requires-Dist: scipy>=1.0.0
Requires-Dist: spglib>1.12.0
Requires-Dist: trainstation>=1.1
Dynamic: license-file
